mtcli_vwap/__init__.py
mtcli_vwap/cli.py
mtcli_vwap/conf.py
mtcli_vwap/controller.py
mtcli_vwap/model.py
mtcli_vwap/plugin.py
mtcli_vwap/view.py
mtcli_vwap-2.0.0.dist-info/entry_points.txt
mtcli_vwap-2.0.0.dist-info/licenses/LICENSE
mtcli_vwap-2.0.0.dist-info/METADATA
mtcli_vwap-2.0.0.dist-info/WHEEL
mtcli_vwap-2.0.0.dist-info/RECORD
