Metadata-Version: 2.4
Name: mtcli-vwap
Version: 2.0.0
Summary: Plugin mtcli da VWAP
License-Expression: GPL-3.0
License-File: LICENSE
Author: Valmir França da Silva
Author-email: vfranca3@gmail.com
Requires-Python: >=3.10,<3.14
Classifier: Programming Language :: Python :: 3
Classifier: Programming Language :: Python :: 3.10
Classifier: Programming Language :: Python :: 3.11
Classifier: Programming Language :: Python :: 3.12
Classifier: Programming Language :: Python :: 3.13
Requires-Dist: click (>=8.3.1,<9.0.0)
Requires-Dist: metatrader5 (>=5.0.5430,<6.0.0)
Requires-Dist: mtcli (>=1.18.1)
Requires-Dist: pandas (>=2.3.3,<3.0.0)
